{
    "train": {
        "0": {
            "loss": 1.7927247423040287,
            "acc": 0.3274
        },
        "1": {
            "loss": 1.4050888115792628,
            "acc": 0.49066
        },
        "2": {
            "loss": 1.2628808224292667,
            "acc": 0.54926
        },
        "3": {
            "loss": 1.1609105643104105,
            "acc": 0.5893
        },
        "4": {
            "loss": 1.0926452893430314,
            "acc": 0.6187
        },
        "5": {
            "loss": 1.0303052732401796,
            "acc": 0.63862
        },
        "6": {
            "loss": 0.9822804353121296,
            "acc": 0.65504
        },
        "7": {
            "loss": 0.95431843742995,
            "acc": 0.66542
        },
        "8": {
            "loss": 0.9165470101644316,
            "acc": 0.6796
        },
        "9": {
            "loss": 0.8877873814014523,
            "acc": 0.69136
        },
        "10": {
            "loss": 0.8698416109889975,
            "acc": 0.69754
        },
        "11": {
            "loss": 0.8422375141507219,
            "acc": 0.70744
        },
        "12": {
            "loss": 0.8269272614318086,
            "acc": 0.71104
        },
        "13": {
            "loss": 0.8134098206944478,
            "acc": 0.71768
        },
        "14": {
            "loss": 0.7969490974150655,
            "acc": 0.72126
        },
        "15": {
            "loss": 0.7841550402933984,
            "acc": 0.72948
        },
        "16": {
            "loss": 0.7681857181327117,
            "acc": 0.73376
        },
        "17": {
            "loss": 0.7573232557767492,
            "acc": 0.7362
        },
        "18": {
            "loss": 0.7504302056701592,
            "acc": 0.73842
        },
        "19": {
            "loss": 0.7346205218216343,
            "acc": 0.7453
        },
        "20": {
            "loss": 0.7289686211387215,
            "acc": 0.74644
        },
        "21": {
            "loss": 0.7197791015553048,
            "acc": 0.75186
        },
        "22": {
            "loss": 0.7152386778760749,
            "acc": 0.7526
        },
        "23": {
            "loss": 0.7081078726159947,
            "acc": 0.75236
        },
        "24": {
            "loss": 0.7008576417518089,
            "acc": 0.75602
        },
        "25": {
            "loss": 0.6897805911653182,
            "acc": 0.76184
        },
        "26": {
            "loss": 0.6847599464304307,
            "acc": 0.76306
        },
        "27": {
            "loss": 0.6849652851176689,
            "acc": 0.7619
        },
        "28": {
            "loss": 0.6784088983560157,
            "acc": 0.7678
        },
        "29": {
            "loss": 0.6747772160850828,
            "acc": 0.76806
        },
        "30": {
            "loss": 0.6622663556462358,
            "acc": 0.7694
        },
        "31": {
            "loss": 0.6723632901678305,
            "acc": 0.76926
        },
        "32": {
            "loss": 0.65963697563047,
            "acc": 0.7711
        },
        "33": {
            "loss": 0.6597560333931233,
            "acc": 0.7698
        },
        "34": {
            "loss": 0.6575626429084622,
            "acc": 0.77148
        },
        "35": {
            "loss": 0.6562651962118076,
            "acc": 0.7767
        },
        "36": {
            "loss": 0.6474083868591377,
            "acc": 0.77562
        },
        "37": {
            "loss": 0.6487100561104162,
            "acc": 0.7777
        },
        "38": {
            "loss": 0.652243938897272,
            "acc": 0.77692
        },
        "39": {
            "loss": 0.6473447656844888,
            "acc": 0.77758
        },
        "40": {
            "loss": 0.6499307676959221,
            "acc": 0.77504
        },
        "41": {
            "loss": 0.6405538821311862,
            "acc": 0.78026
        },
        "42": {
            "loss": 0.6403814913976528,
            "acc": 0.78028
        },
        "43": {
            "loss": 0.6407658527116946,
            "acc": 0.77932
        },
        "44": {
            "loss": 0.6432330378943392,
            "acc": 0.78084
        },
        "45": {
            "loss": 0.640833132254803,
            "acc": 0.78158
        },
        "46": {
            "loss": 0.6289837466328955,
            "acc": 0.78436
        },
        "47": {
            "loss": 0.6282223187139272,
            "acc": 0.78704
        },
        "48": {
            "loss": 0.6335519638360309,
            "acc": 0.78382
        },
        "49": {
            "loss": 0.6238865796714792,
            "acc": 0.78492
        },
        "50": {
            "loss": 0.6325400456443162,
            "acc": 0.78254
        },
        "51": {
            "loss": 0.6248269900489036,
            "acc": 0.7865
        },
        "52": {
            "loss": 0.623869929091095,
            "acc": 0.78632
        },
        "53": {
            "loss": 0.6222921189139871,
            "acc": 0.78736
        },
        "54": {
            "loss": 0.6365834370141139,
            "acc": 0.78208
        },
        "55": {
            "loss": 0.6263861272036267,
            "acc": 0.78576
        },
        "56": {
            "loss": 0.6220382229446451,
            "acc": 0.787
        },
        "57": {
            "loss": 0.6239749053707513,
            "acc": 0.78618
        },
        "58": {
            "loss": 0.6280466005625323,
            "acc": 0.7856
        },
        "59": {
            "loss": 0.6271312825972467,
            "acc": 0.78646
        },
        "60": {
            "loss": 0.6253504740917469,
            "acc": 0.78864
        },
        "61": {
            "loss": 0.6282034733563738,
            "acc": 0.78918
        },
        "62": {
            "loss": 0.6201384604129645,
            "acc": 0.7896
        },
        "63": {
            "loss": 0.6259544373625685,
            "acc": 0.78602
        },
        "64": {
            "loss": 0.6213369772714727,
            "acc": 0.79018
        },
        "65": {
            "loss": 0.6317224199967006,
            "acc": 0.78666
        },
        "66": {
            "loss": 0.6195211626989457,
            "acc": 0.79162
        },
        "67": {
            "loss": 0.614397542784586,
            "acc": 0.79234
        },
        "68": {
            "loss": 0.6205266815469698,
            "acc": 0.78902
        },
        "69": {
            "loss": 0.6212902742121226,
            "acc": 0.79124
        },
        "70": {
            "loss": 0.6043872302755371,
            "acc": 0.79636
        },
        "71": {
            "loss": 0.6232398453423434,
            "acc": 0.7915
        },
        "72": {
            "loss": 0.6151573829486242,
            "acc": 0.79466
        },
        "73": {
            "loss": 0.6160603895059327,
            "acc": 0.79288
        },
        "74": {
            "loss": 0.6138381187415793,
            "acc": 0.79138
        },
        "75": {
            "loss": 0.6180366201473929,
            "acc": 0.79426
        },
        "76": {
            "loss": 0.6089852390539311,
            "acc": 0.79522
        },
        "77": {
            "loss": 0.6087704474663795,
            "acc": 0.7956
        },
        "78": {
            "loss": 0.6169911376045792,
            "acc": 0.79362
        },
        "79": {
            "loss": 0.6196938434525219,
            "acc": 0.79462
        },
        "80": {
            "loss": 0.5972428389674868,
            "acc": 0.79868
        },
        "81": {
            "loss": 0.6056762323964893,
            "acc": 0.79702
        },
        "82": {
            "loss": 0.6048445030094107,
            "acc": 0.79832
        },
        "83": {
            "loss": 0.6048757187698198,
            "acc": 0.7976
        },
        "84": {
            "loss": 0.6064112193291754,
            "acc": 0.79958
        },
        "85": {
            "loss": 0.6022732799010508,
            "acc": 0.79846
        },
        "86": {
            "loss": 0.6024911236732512,
            "acc": 0.7986
        },
        "87": {
            "loss": 0.5999617658917556,
            "acc": 0.80032
        },
        "88": {
            "loss": 0.6004131530099512,
            "acc": 0.79658
        },
        "89": {
            "loss": 0.599444913589741,
            "acc": 0.7999
        },
        "90": {
            "loss": 0.5983326497590146,
            "acc": 0.79844
        },
        "91": {
            "loss": 0.5950759449578307,
            "acc": 0.80118
        },
        "92": {
            "loss": 0.5961347492911931,
            "acc": 0.80052
        },
        "93": {
            "loss": 0.5933502169368822,
            "acc": 0.80158
        },
        "94": {
            "loss": 0.5978613761075012,
            "acc": 0.7997
        },
        "95": {
            "loss": 0.5994650365598976,
            "acc": 0.80088
        },
        "96": {
            "loss": 0.6000358783985342,
            "acc": 0.79832
        },
        "97": {
            "loss": 0.5954679828470625,
            "acc": 0.80102
        },
        "98": {
            "loss": 0.595234846519997,
            "acc": 0.7999
        },
        "99": {
            "loss": 0.596821403411953,
            "acc": 0.80146
        },
        "100": {
            "loss": 0.42204995632476516,
            "acc": 0.85822
        },
        "101": {
            "loss": 0.3587336582905801,
            "acc": 0.87476
        },
        "102": {
            "loss": 0.33036895385940973,
            "acc": 0.8845
        },
        "103": {
            "loss": 0.3152009945391389,
            "acc": 0.8895
        },
        "104": {
            "loss": 0.3008074238324714,
            "acc": 0.89424
        },
        "105": {
            "loss": 0.29045568749575357,
            "acc": 0.8974
        },
        "106": {
            "loss": 0.2750928286091446,
            "acc": 0.903
        },
        "107": {
            "loss": 0.26753149118722247,
            "acc": 0.90492
        },
        "108": {
            "loss": 0.2580647278777169,
            "acc": 0.90762
        },
        "109": {
            "loss": 0.2508717468175132,
            "acc": 0.91132
        },
        "110": {
            "loss": 0.24265363812446594,
            "acc": 0.91314
        },
        "111": {
            "loss": 0.23463981977813994,
            "acc": 0.91658
        },
        "112": {
            "loss": 0.23125002319779236,
            "acc": 0.91848
        },
        "113": {
            "loss": 0.21750559638756925,
            "acc": 0.92216
        },
        "114": {
            "loss": 0.21804614742393688,
            "acc": 0.92242
        },
        "115": {
            "loss": 0.20881537003133,
            "acc": 0.9249
        },
        "116": {
            "loss": 0.2044252817092649,
            "acc": 0.9265
        },
        "117": {
            "loss": 0.19628531937404056,
            "acc": 0.92942
        },
        "118": {
            "loss": 0.19334878227518648,
            "acc": 0.93124
        },
        "119": {
            "loss": 0.18885169999526286,
            "acc": 0.93206
        },
        "120": {
            "loss": 0.18332673841730104,
            "acc": 0.93496
        },
        "121": {
            "loss": 0.17744107588249095,
            "acc": 0.93566
        },
        "122": {
            "loss": 0.17356319817931146,
            "acc": 0.93914
        },
        "123": {
            "loss": 0.1664640898423274,
            "acc": 0.9402
        },
        "124": {
            "loss": 0.1628143487645842,
            "acc": 0.94094
        },
        "125": {
            "loss": 0.15858434013965184,
            "acc": 0.94424
        },
        "126": {
            "loss": 0.15441372394180664,
            "acc": 0.94438
        },
        "127": {
            "loss": 0.15561762355896822,
            "acc": 0.94446
        },
        "128": {
            "loss": 0.15036418125071488,
            "acc": 0.9459
        },
        "129": {
            "loss": 0.14456422008631176,
            "acc": 0.94782
        },
        "130": {
            "loss": 0.14191590802139029,
            "acc": 0.94964
        },
        "131": {
            "loss": 0.1360928505430441,
            "acc": 0.95132
        },
        "132": {
            "loss": 0.13191135400129705,
            "acc": 0.95406
        },
        "133": {
            "loss": 0.13088520496245235,
            "acc": 0.95378
        },
        "134": {
            "loss": 0.12581504110599417,
            "acc": 0.95646
        },
        "135": {
            "loss": 0.12655256443735582,
            "acc": 0.955
        },
        "136": {
            "loss": 0.1186769659847707,
            "acc": 0.95712
        },
        "137": {
            "loss": 0.11708593503822146,
            "acc": 0.95858
        },
        "138": {
            "loss": 0.1144346640161846,
            "acc": 0.96074
        },
        "139": {
            "loss": 0.10934926907215124,
            "acc": 0.9612
        },
        "140": {
            "loss": 0.10971842673333253,
            "acc": 0.96174
        },
        "141": {
            "loss": 0.108540952677274,
            "acc": 0.9625
        },
        "142": {
            "loss": 0.10188753631852014,
            "acc": 0.96402
        },
        "143": {
            "loss": 0.10151636849641038,
            "acc": 0.9641
        },
        "144": {
            "loss": 0.09696633563093517,
            "acc": 0.96638
        },
        "145": {
            "loss": 0.09749553849934922,
            "acc": 0.966
        },
        "146": {
            "loss": 0.09173485591931416,
            "acc": 0.96844
        },
        "147": {
            "loss": 0.09116438895825991,
            "acc": 0.96866
        },
        "148": {
            "loss": 0.08579113092416388,
            "acc": 0.97
        },
        "149": {
            "loss": 0.08872881021036212,
            "acc": 0.97016
        },
        "150": {
            "loss": 0.07796166841979221,
            "acc": 0.97348
        },
        "151": {
            "loss": 0.07405551779024361,
            "acc": 0.97398
        },
        "152": {
            "loss": 0.07427658565590144,
            "acc": 0.975
        },
        "153": {
            "loss": 0.07229576499708702,
            "acc": 0.97578
        },
        "154": {
            "loss": 0.07099494189405076,
            "acc": 0.97586
        },
        "155": {
            "loss": 0.06927698272782976,
            "acc": 0.97706
        },
        "156": {
            "loss": 0.06757392433693495,
            "acc": 0.97736
        },
        "157": {
            "loss": 0.06859698025342982,
            "acc": 0.97726
        },
        "158": {
            "loss": 0.0669978554372478,
            "acc": 0.9767
        },
        "159": {
            "loss": 0.06753864578540673,
            "acc": 0.97698
        },
        "160": {
            "loss": 0.06625687676098417,
            "acc": 0.97722
        },
        "161": {
            "loss": 0.06431975585106008,
            "acc": 0.97838
        },
        "162": {
            "loss": 0.06297206250078918,
            "acc": 0.97912
        },
        "163": {
            "loss": 0.06645296967309683,
            "acc": 0.97684
        },
        "164": {
            "loss": 0.06362183037859476,
            "acc": 0.97908
        },
        "165": {
            "loss": 0.06728781214045823,
            "acc": 0.97762
        },
        "166": {
            "loss": 0.06297365228747925,
            "acc": 0.97888
        },
        "167": {
            "loss": 0.06163607962677241,
            "acc": 0.97926
        },
        "168": {
            "loss": 0.06289203184873551,
            "acc": 0.97864
        },
        "169": {
            "loss": 0.06215632358885101,
            "acc": 0.9795
        },
        "170": {
            "loss": 0.06213219169422489,
            "acc": 0.9787
        },
        "171": {
            "loss": 0.060701427905036666,
            "acc": 0.97962
        },
        "172": {
            "loss": 0.06248793999909821,
            "acc": 0.97916
        },
        "173": {
            "loss": 0.060373729595061765,
            "acc": 0.9796
        },
        "174": {
            "loss": 0.06186716334746622,
            "acc": 0.9794
        },
        "175": {
            "loss": 0.06159969497843624,
            "acc": 0.97936
        },
        "176": {
            "loss": 0.05770901164463948,
            "acc": 0.98084
        },
        "177": {
            "loss": 0.06116962718212848,
            "acc": 0.97974
        },
        "178": {
            "loss": 0.05952199013270152,
            "acc": 0.97986
        },
        "179": {
            "loss": 0.05871917105868192,
            "acc": 0.98018
        },
        "180": {
            "loss": 0.05679397679188901,
            "acc": 0.98092
        },
        "181": {
            "loss": 0.05916363276217295,
            "acc": 0.98032
        },
        "182": {
            "loss": 0.05465185690833175,
            "acc": 0.98142
        },
        "183": {
            "loss": 0.05445182568076855,
            "acc": 0.9816
        },
        "184": {
            "loss": 0.05628440460509351,
            "acc": 0.98104
        },
        "185": {
            "loss": 0.056730406370747576,
            "acc": 0.98128
        },
        "186": {
            "loss": 0.056780057273271595,
            "acc": 0.98084
        },
        "187": {
            "loss": 0.05516813623021021,
            "acc": 0.98146
        },
        "188": {
            "loss": 0.05824573985312868,
            "acc": 0.98108
        },
        "189": {
            "loss": 0.053655599313014,
            "acc": 0.98138
        },
        "190": {
            "loss": 0.05527874773315838,
            "acc": 0.9813
        },
        "191": {
            "loss": 0.05489211980148655,
            "acc": 0.98216
        },
        "192": {
            "loss": 0.052680883416072334,
            "acc": 0.98254
        },
        "193": {
            "loss": 0.05512138927722221,
            "acc": 0.98206
        },
        "194": {
            "loss": 0.053474969449726975,
            "acc": 0.98286
        },
        "195": {
            "loss": 0.053898031916231146,
            "acc": 0.98174
        },
        "196": {
            "loss": 0.05360183413223842,
            "acc": 0.9826
        },
        "197": {
            "loss": 0.053446239698916445,
            "acc": 0.98254
        },
        "198": {
            "loss": 0.051509114568267025,
            "acc": 0.9826
        },
        "199": {
            "loss": 0.05317762019732,
            "acc": 0.98208
        },
        "200": {
            "loss": 0.05132887805419047,
            "acc": 0.98248
        },
        "201": {
            "loss": 0.05271781881427978,
            "acc": 0.98294
        },
        "202": {
            "loss": 0.05111199266770307,
            "acc": 0.98298
        },
        "203": {
            "loss": 0.05121832356676269,
            "acc": 0.9831
        },
        "204": {
            "loss": 0.05173231020469762,
            "acc": 0.98308
        },
        "205": {
            "loss": 0.04953906512188027,
            "acc": 0.98374
        },
        "206": {
            "loss": 0.052628595827390316,
            "acc": 0.98274
        },
        "207": {
            "loss": 0.05166366836413398,
            "acc": 0.98272
        },
        "208": {
            "loss": 0.0534334305216513,
            "acc": 0.9825
        },
        "209": {
            "loss": 0.05285037948947657,
            "acc": 0.98296
        },
        "210": {
            "loss": 0.05121819820026379,
            "acc": 0.98356
        },
        "211": {
            "loss": 0.05231716451437577,
            "acc": 0.9826
        },
        "212": {
            "loss": 0.05162253460187055,
            "acc": 0.98296
        },
        "213": {
            "loss": 0.0507561983332238,
            "acc": 0.98314
        },
        "214": {
            "loss": 0.05352090878645554,
            "acc": 0.98272
        },
        "215": {
            "loss": 0.04951249815695121,
            "acc": 0.98382
        },
        "216": {
            "loss": 0.05094823516700465,
            "acc": 0.98388
        },
        "217": {
            "loss": 0.05230531042389324,
            "acc": 0.98306
        },
        "218": {
            "loss": 0.050214813942389795,
            "acc": 0.9836
        },
        "219": {
            "loss": 0.048490133468785786,
            "acc": 0.98394
        },
        "220": {
            "loss": 0.052005484266697294,
            "acc": 0.98324
        },
        "221": {
            "loss": 0.048251027802286475,
            "acc": 0.98384
        },
        "222": {
            "loss": 0.051608863053247904,
            "acc": 0.9825
        },
        "223": {
            "loss": 0.051899569118609816,
            "acc": 0.983
        },
        "224": {
            "loss": 0.05082210745005047,
            "acc": 0.98352
        },
        "225": {
            "loss": 0.050517357349910245,
            "acc": 0.98358
        },
        "226": {
            "loss": 0.048359327429138566,
            "acc": 0.9841
        },
        "227": {
            "loss": 0.05086374915469333,
            "acc": 0.98364
        },
        "228": {
            "loss": 0.04862415518425881,
            "acc": 0.98466
        },
        "229": {
            "loss": 0.05101624774553663,
            "acc": 0.98356
        },
        "230": {
            "loss": 0.05207506752908801,
            "acc": 0.98278
        },
        "231": {
            "loss": 0.05279862619412448,
            "acc": 0.98264
        },
        "232": {
            "loss": 0.051269891362189485,
            "acc": 0.98298
        },
        "233": {
            "loss": 0.05175029859304085,
            "acc": 0.98338
        },
        "234": {
            "loss": 0.051178402253105056,
            "acc": 0.98348
        },
        "235": {
            "loss": 0.05091692414253836,
            "acc": 0.9839
        },
        "236": {
            "loss": 0.050753615379733656,
            "acc": 0.98242
        },
        "237": {
            "loss": 0.050238673479946525,
            "acc": 0.9832
        },
        "238": {
            "loss": 0.04985128738738768,
            "acc": 0.98362
        },
        "239": {
            "loss": 0.050618630345634484,
            "acc": 0.98294
        },
        "240": {
            "loss": 0.04880815306606957,
            "acc": 0.98354
        },
        "241": {
            "loss": 0.05389307559613148,
            "acc": 0.98178
        },
        "242": {
            "loss": 0.0480961719756503,
            "acc": 0.98368
        },
        "243": {
            "loss": 0.049864980233761735,
            "acc": 0.9838
        },
        "244": {
            "loss": 0.05148554272959223,
            "acc": 0.98316
        },
        "245": {
            "loss": 0.04961268440641634,
            "acc": 0.98418
        },
        "246": {
            "loss": 0.05024396570142158,
            "acc": 0.98358
        },
        "247": {
            "loss": 0.047209344051606816,
            "acc": 0.98456
        },
        "248": {
            "loss": 0.049212285792669445,
            "acc": 0.9837
        },
        "249": {
            "loss": 0.051363436693368514,
            "acc": 0.98312
        }
    },
    "test": {
        "0": {
            "loss": 1.5066683053970338,
            "acc": 0.4428
        },
        "1": {
            "loss": 1.299984357357025,
            "acc": 0.526
        },
        "3": {
            "loss": 1.1667338955402373,
            "acc": 0.5941
        },
        "5": {
            "loss": 0.9967246997356415,
            "acc": 0.6591
        },
        "7": {
            "loss": 0.930180879831314,
            "acc": 0.6783
        },
        "9": {
            "loss": 0.928803207874298,
            "acc": 0.6881
        },
        "11": {
            "loss": 0.8836678349971772,
            "acc": 0.6954
        },
        "13": {
            "loss": 0.9256431627273559,
            "acc": 0.6879
        },
        "15": {
            "loss": 0.8452435457706451,
            "acc": 0.7138
        },
        "17": {
            "loss": 0.8577192497253417,
            "acc": 0.7074
        },
        "19": {
            "loss": 0.8508969581127167,
            "acc": 0.7144
        },
        "21": {
            "loss": 0.8680330669879913,
            "acc": 0.7016
        },
        "23": {
            "loss": 0.8094906091690064,
            "acc": 0.7291
        },
        "25": {
            "loss": 0.8369880938529968,
            "acc": 0.7203
        },
        "27": {
            "loss": 0.8121780252456665,
            "acc": 0.7289
        },
        "29": {
            "loss": 0.8206109726428985,
            "acc": 0.7312
        },
        "31": {
            "loss": 0.8680888903141022,
            "acc": 0.7124
        },
        "33": {
            "loss": 0.802005250453949,
            "acc": 0.7389
        },
        "35": {
            "loss": 0.837881555557251,
            "acc": 0.7287
        },
        "37": {
            "loss": 0.8458982360363007,
            "acc": 0.7271
        },
        "39": {
            "loss": 0.8329355454444886,
            "acc": 0.7275
        },
        "41": {
            "loss": 0.8441623520851135,
            "acc": 0.7216
        },
        "43": {
            "loss": 0.8045354890823364,
            "acc": 0.7425
        },
        "45": {
            "loss": 0.8528226470947265,
            "acc": 0.7199
        },
        "47": {
            "loss": 0.8198969960212708,
            "acc": 0.7314
        },
        "49": {
            "loss": 0.8325251173973084,
            "acc": 0.7344
        },
        "51": {
            "loss": 0.8240216135978699,
            "acc": 0.7352
        },
        "53": {
            "loss": 0.8302910017967224,
            "acc": 0.7281
        },
        "55": {
            "loss": 0.8942530453205109,
            "acc": 0.7235
        },
        "57": {
            "loss": 0.8557038354873657,
            "acc": 0.7218
        },
        "59": {
            "loss": 0.8581531012058258,
            "acc": 0.7237
        },
        "61": {
            "loss": 0.8263269066810608,
            "acc": 0.7334
        },
        "63": {
            "loss": 0.8494057834148407,
            "acc": 0.7329
        },
        "65": {
            "loss": 0.8753034424781799,
            "acc": 0.7228
        },
        "67": {
            "loss": 0.8738056969642639,
            "acc": 0.7254
        },
        "69": {
            "loss": 0.8845518064498902,
            "acc": 0.7306
        },
        "71": {
            "loss": 0.8705136144161224,
            "acc": 0.7331
        },
        "73": {
            "loss": 0.8870745646953583,
            "acc": 0.7259
        },
        "75": {
            "loss": 0.8314738714694977,
            "acc": 0.734
        },
        "77": {
            "loss": 0.868009672164917,
            "acc": 0.7282
        },
        "79": {
            "loss": 0.8762699592113495,
            "acc": 0.7316
        },
        "81": {
            "loss": 0.8710715878009796,
            "acc": 0.7212
        },
        "83": {
            "loss": 0.8437304759025573,
            "acc": 0.7332
        },
        "85": {
            "loss": 0.8405177640914917,
            "acc": 0.7361
        },
        "87": {
            "loss": 0.8224825191497803,
            "acc": 0.7395
        },
        "89": {
            "loss": 0.8669422662258148,
            "acc": 0.7399
        },
        "91": {
            "loss": 0.8499605214595795,
            "acc": 0.7353
        },
        "93": {
            "loss": 0.8517603182792663,
            "acc": 0.7371
        },
        "95": {
            "loss": 0.8960259306430817,
            "acc": 0.7258
        },
        "97": {
            "loss": 0.8421322929859162,
            "acc": 0.7375
        },
        "99": {
            "loss": 0.8683143699169159,
            "acc": 0.7414
        },
        "101": {
            "loss": 0.7549202001094818,
            "acc": 0.7736
        },
        "103": {
            "loss": 0.7617602974176407,
            "acc": 0.778
        },
        "105": {
            "loss": 0.7807475370168686,
            "acc": 0.7783
        },
        "107": {
            "loss": 0.7894242215156555,
            "acc": 0.7796
        },
        "109": {
            "loss": 0.8203316926956177,
            "acc": 0.7777
        },
        "111": {
            "loss": 0.829135046005249,
            "acc": 0.7802
        },
        "113": {
            "loss": 0.8466062867641448,
            "acc": 0.78
        },
        "115": {
            "loss": 0.8355541932582855,
            "acc": 0.7852
        },
        "117": {
            "loss": 0.8772247660160065,
            "acc": 0.7774
        },
        "119": {
            "loss": 0.8879680645465851,
            "acc": 0.7761
        },
        "121": {
            "loss": 0.9083560490608216,
            "acc": 0.7804
        },
        "123": {
            "loss": 0.9299273407459259,
            "acc": 0.7807
        },
        "125": {
            "loss": 0.9503413879871369,
            "acc": 0.7811
        },
        "127": {
            "loss": 0.9558182835578919,
            "acc": 0.7815
        },
        "129": {
            "loss": 0.979148519039154,
            "acc": 0.7808
        },
        "131": {
            "loss": 0.9976248466968536,
            "acc": 0.7809
        },
        "133": {
            "loss": 1.0231937170028687,
            "acc": 0.7789
        },
        "135": {
            "loss": 1.0220300841331482,
            "acc": 0.7835
        },
        "137": {
            "loss": 1.059614450931549,
            "acc": 0.777
        },
        "139": {
            "loss": 1.0747314620018005,
            "acc": 0.7796
        },
        "141": {
            "loss": 1.0875000035762787,
            "acc": 0.7786
        },
        "143": {
            "loss": 1.0989546585083008,
            "acc": 0.7789
        },
        "145": {
            "loss": 1.1227240657806397,
            "acc": 0.7792
        },
        "147": {
            "loss": 1.1440998637676238,
            "acc": 0.7813
        },
        "149": {
            "loss": 1.1565993046760559,
            "acc": 0.7804
        },
        "151": {
            "loss": 1.1490769588947296,
            "acc": 0.7849
        },
        "153": {
            "loss": 1.1511481738090514,
            "acc": 0.7857
        },
        "155": {
            "loss": 1.1574477851390839,
            "acc": 0.7867
        },
        "157": {
            "loss": 1.1580652272701264,
            "acc": 0.7859
        },
        "159": {
            "loss": 1.1641612684726714,
            "acc": 0.785
        },
        "161": {
            "loss": 1.1711568927764893,
            "acc": 0.7861
        },
        "163": {
            "loss": 1.1701063001155854,
            "acc": 0.7863
        },
        "165": {
            "loss": 1.1742875933647157,
            "acc": 0.7844
        },
        "167": {
            "loss": 1.1833464014530182,
            "acc": 0.7844
        },
        "169": {
            "loss": 1.188370760679245,
            "acc": 0.7844
        },
        "171": {
            "loss": 1.1886418175697326,
            "acc": 0.7835
        },
        "173": {
            "loss": 1.1921948647499085,
            "acc": 0.7849
        },
        "175": {
            "loss": 1.1956936132907867,
            "acc": 0.7838
        },
        "177": {
            "loss": 1.201804096698761,
            "acc": 0.7838
        },
        "179": {
            "loss": 1.2026497662067412,
            "acc": 0.784
        },
        "181": {
            "loss": 1.209098093509674,
            "acc": 0.7852
        },
        "183": {
            "loss": 1.2146171748638153,
            "acc": 0.7846
        },
        "185": {
            "loss": 1.2182517492771148,
            "acc": 0.7844
        },
        "187": {
            "loss": 1.218088595867157,
            "acc": 0.7854
        },
        "189": {
            "loss": 1.2230948090553284,
            "acc": 0.7859
        },
        "191": {
            "loss": 1.2282534217834473,
            "acc": 0.7845
        },
        "193": {
            "loss": 1.2333967864513398,
            "acc": 0.7836
        },
        "195": {
            "loss": 1.2339844274520875,
            "acc": 0.7843
        },
        "197": {
            "loss": 1.2398743331432343,
            "acc": 0.7831
        },
        "199": {
            "loss": 1.2419775938987732,
            "acc": 0.7845
        },
        "201": {
            "loss": 1.24201464176178,
            "acc": 0.7848
        },
        "203": {
            "loss": 1.2428718495368958,
            "acc": 0.7847
        },
        "205": {
            "loss": 1.2426679372787475,
            "acc": 0.7846
        },
        "207": {
            "loss": 1.2427963244915008,
            "acc": 0.7855
        },
        "209": {
            "loss": 1.242898691892624,
            "acc": 0.7852
        },
        "211": {
            "loss": 1.2426052975654602,
            "acc": 0.7851
        },
        "213": {
            "loss": 1.2426521408557891,
            "acc": 0.7854
        },
        "215": {
            "loss": 1.242915884256363,
            "acc": 0.7852
        },
        "217": {
            "loss": 1.243372793197632,
            "acc": 0.7853
        },
        "219": {
            "loss": 1.2440507423877716,
            "acc": 0.785
        },
        "221": {
            "loss": 1.2449248003959656,
            "acc": 0.7857
        },
        "223": {
            "loss": 1.2452476167678832,
            "acc": 0.7858
        },
        "225": {
            "loss": 1.2464732336997986,
            "acc": 0.7855
        },
        "227": {
            "loss": 1.2471030926704407,
            "acc": 0.7858
        },
        "229": {
            "loss": 1.2465256690979003,
            "acc": 0.7856
        },
        "231": {
            "loss": 1.2469039690494537,
            "acc": 0.7856
        },
        "233": {
            "loss": 1.246533957719803,
            "acc": 0.7857
        },
        "235": {
            "loss": 1.2470343863964082,
            "acc": 0.7857
        },
        "237": {
            "loss": 1.2476743102073669,
            "acc": 0.7851
        },
        "239": {
            "loss": 1.247916522026062,
            "acc": 0.7857
        },
        "241": {
            "loss": 1.2481089782714845,
            "acc": 0.7856
        },
        "243": {
            "loss": 1.2485954666137695,
            "acc": 0.7855
        },
        "245": {
            "loss": 1.248091697692871,
            "acc": 0.7852
        },
        "247": {
            "loss": 1.2485821187496184,
            "acc": 0.7855
        },
        "249": {
            "loss": 1.2478015851974487,
            "acc": 0.7858
        }
    },
    "info": {
        "best_epoch": 155,
        "best_acc": 78.67,
        "n_params": 3504650
    }
}