{
    "train": {
        "0": {
            "loss": 1.6114851333905973,
            "acc": 0.4033
        },
        "1": {
            "loss": 1.263361328550617,
            "acc": 0.5449
        },
        "2": {
            "loss": 1.108086373799902,
            "acc": 0.6036
        },
        "3": {
            "loss": 1.000251992431748,
            "acc": 0.64912
        },
        "4": {
            "loss": 0.8818743082568469,
            "acc": 0.69172
        },
        "5": {
            "loss": 0.818887820938969,
            "acc": 0.71648
        },
        "6": {
            "loss": 0.7487531725098105,
            "acc": 0.74226
        },
        "7": {
            "loss": 0.6990780292264641,
            "acc": 0.75832
        },
        "8": {
            "loss": 0.6618084733748375,
            "acc": 0.7714
        },
        "9": {
            "loss": 0.623563321578838,
            "acc": 0.78592
        },
        "10": {
            "loss": 0.5963953686949542,
            "acc": 0.79618
        },
        "11": {
            "loss": 0.5607532178197066,
            "acc": 0.8075
        },
        "12": {
            "loss": 0.5344171953170805,
            "acc": 0.81588
        },
        "13": {
            "loss": 0.511189977531238,
            "acc": 0.82502
        },
        "14": {
            "loss": 0.49553496201934716,
            "acc": 0.83092
        },
        "15": {
            "loss": 0.4793055319343991,
            "acc": 0.8349
        },
        "16": {
            "loss": 0.4575016420058277,
            "acc": 0.8429
        },
        "17": {
            "loss": 0.4372190620435778,
            "acc": 0.84984
        },
        "18": {
            "loss": 0.4296738147125829,
            "acc": 0.85292
        },
        "19": {
            "loss": 0.425702236040169,
            "acc": 0.85516
        },
        "20": {
            "loss": 0.4125832526961251,
            "acc": 0.86014
        },
        "21": {
            "loss": 0.4005509074920279,
            "acc": 0.86328
        },
        "22": {
            "loss": 0.39576128578704334,
            "acc": 0.86368
        },
        "23": {
            "loss": 0.38833376208839515,
            "acc": 0.86852
        },
        "24": {
            "loss": 0.3801282071091635,
            "acc": 0.86976
        },
        "25": {
            "loss": 0.3680796469264018,
            "acc": 0.8742
        },
        "26": {
            "loss": 0.3548194126171224,
            "acc": 0.8769
        },
        "27": {
            "loss": 0.35024192292824424,
            "acc": 0.87948
        },
        "28": {
            "loss": 0.33951596286900515,
            "acc": 0.88238
        },
        "29": {
            "loss": 0.3360625690663867,
            "acc": 0.88348
        },
        "30": {
            "loss": 0.33520833713471737,
            "acc": 0.88524
        },
        "31": {
            "loss": 0.3284151821261477,
            "acc": 0.88744
        },
        "32": {
            "loss": 0.3210517871753334,
            "acc": 0.88884
        },
        "33": {
            "loss": 0.319735865458808,
            "acc": 0.89062
        },
        "34": {
            "loss": 0.31438837316639895,
            "acc": 0.89106
        },
        "35": {
            "loss": 0.31666550787208636,
            "acc": 0.8899
        },
        "36": {
            "loss": 0.3018259534521786,
            "acc": 0.8948
        },
        "37": {
            "loss": 0.30385191182193855,
            "acc": 0.89468
        },
        "38": {
            "loss": 0.3000757841731581,
            "acc": 0.8971
        },
        "39": {
            "loss": 0.2952165272077331,
            "acc": 0.89986
        },
        "40": {
            "loss": 0.29065560206504126,
            "acc": 0.9008
        },
        "41": {
            "loss": 0.2903475653942284,
            "acc": 0.90022
        },
        "42": {
            "loss": 0.29246444920139847,
            "acc": 0.8982
        },
        "43": {
            "loss": 0.288943508206426,
            "acc": 0.90016
        },
        "44": {
            "loss": 0.2847905751613095,
            "acc": 0.90146
        },
        "45": {
            "loss": 0.27772626684754703,
            "acc": 0.90398
        },
        "46": {
            "loss": 0.27301453164471384,
            "acc": 0.9069
        },
        "47": {
            "loss": 0.2729923575544906,
            "acc": 0.9054
        },
        "48": {
            "loss": 0.26510586764882593,
            "acc": 0.9091
        },
        "49": {
            "loss": 0.27053225145239357,
            "acc": 0.90576
        },
        "50": {
            "loss": 0.2648484107783383,
            "acc": 0.90884
        },
        "51": {
            "loss": 0.26128478615027867,
            "acc": 0.90932
        },
        "52": {
            "loss": 0.2591601864379995,
            "acc": 0.91144
        },
        "53": {
            "loss": 0.25356052558669046,
            "acc": 0.91248
        },
        "54": {
            "loss": 0.25898510878881836,
            "acc": 0.91058
        },
        "55": {
            "loss": 0.2501078998608053,
            "acc": 0.91304
        },
        "56": {
            "loss": 0.251673353088024,
            "acc": 0.91288
        },
        "57": {
            "loss": 0.24754850775994303,
            "acc": 0.9138
        },
        "58": {
            "loss": 0.24517557084026848,
            "acc": 0.91626
        },
        "59": {
            "loss": 0.24262198674328186,
            "acc": 0.91524
        },
        "60": {
            "loss": 0.23468326481864277,
            "acc": 0.91784
        },
        "61": {
            "loss": 0.23826968940475102,
            "acc": 0.91786
        },
        "62": {
            "loss": 0.23898150198294987,
            "acc": 0.91748
        },
        "63": {
            "loss": 0.24099981908679313,
            "acc": 0.91688
        },
        "64": {
            "loss": 0.23295792994444328,
            "acc": 0.91918
        },
        "65": {
            "loss": 0.23063401489154153,
            "acc": 0.92082
        },
        "66": {
            "loss": 0.23213965129440703,
            "acc": 0.92006
        },
        "67": {
            "loss": 0.2303066612661952,
            "acc": 0.92142
        },
        "68": {
            "loss": 0.22643236627282998,
            "acc": 0.92224
        },
        "69": {
            "loss": 0.2314806406188499,
            "acc": 0.91942
        },
        "70": {
            "loss": 0.2249832395321268,
            "acc": 0.9225
        },
        "71": {
            "loss": 0.22381546651310932,
            "acc": 0.92136
        },
        "72": {
            "loss": 0.21941245859846129,
            "acc": 0.9248
        },
        "73": {
            "loss": 0.22643024121861324,
            "acc": 0.92154
        },
        "74": {
            "loss": 0.21751726089078752,
            "acc": 0.92522
        },
        "75": {
            "loss": 0.21600927313422913,
            "acc": 0.9252
        },
        "76": {
            "loss": 0.21970343940398274,
            "acc": 0.9238
        },
        "77": {
            "loss": 0.20746615187972403,
            "acc": 0.92872
        },
        "78": {
            "loss": 0.21378748526658548,
            "acc": 0.92464
        },
        "79": {
            "loss": 0.20904551351161868,
            "acc": 0.92762
        },
        "80": {
            "loss": 0.20382162284515704,
            "acc": 0.92822
        },
        "81": {
            "loss": 0.2064843415794775,
            "acc": 0.92848
        },
        "82": {
            "loss": 0.20325258957303088,
            "acc": 0.92934
        },
        "83": {
            "loss": 0.20265115187753496,
            "acc": 0.9299
        },
        "84": {
            "loss": 0.1966704320724663,
            "acc": 0.93216
        },
        "85": {
            "loss": 0.20249275373452155,
            "acc": 0.93066
        },
        "86": {
            "loss": 0.20510116718766636,
            "acc": 0.92882
        },
        "87": {
            "loss": 0.19067284047527386,
            "acc": 0.93284
        },
        "88": {
            "loss": 0.19098834910661058,
            "acc": 0.93364
        },
        "89": {
            "loss": 0.1962715045494192,
            "acc": 0.93108
        },
        "90": {
            "loss": 0.19120605558614293,
            "acc": 0.93352
        },
        "91": {
            "loss": 0.18933253231294014,
            "acc": 0.9343
        },
        "92": {
            "loss": 0.1847017726687062,
            "acc": 0.93566
        },
        "93": {
            "loss": 0.18773053958059271,
            "acc": 0.9344
        },
        "94": {
            "loss": 0.18099368293114634,
            "acc": 0.93658
        },
        "95": {
            "loss": 0.18399193202671799,
            "acc": 0.93776
        },
        "96": {
            "loss": 0.18154029229946453,
            "acc": 0.93702
        },
        "97": {
            "loss": 0.1815761557168058,
            "acc": 0.93686
        },
        "98": {
            "loss": 0.1795637092036207,
            "acc": 0.93708
        },
        "99": {
            "loss": 0.17568221722569916,
            "acc": 0.93938
        },
        "100": {
            "loss": 0.17150184464500384,
            "acc": 0.94108
        },
        "101": {
            "loss": 0.1783908103566493,
            "acc": 0.93894
        },
        "102": {
            "loss": 0.16494913337290135,
            "acc": 0.943
        },
        "103": {
            "loss": 0.16952234082629003,
            "acc": 0.9415
        },
        "104": {
            "loss": 0.1677832571918245,
            "acc": 0.94096
        },
        "105": {
            "loss": 0.17101064307229294,
            "acc": 0.9411
        },
        "106": {
            "loss": 0.1707756430710978,
            "acc": 0.94158
        },
        "107": {
            "loss": 0.16736493992340534,
            "acc": 0.94208
        },
        "108": {
            "loss": 0.17248799529907954,
            "acc": 0.93966
        },
        "109": {
            "loss": 0.16604048537704952,
            "acc": 0.94282
        },
        "110": {
            "loss": 0.16323840186533417,
            "acc": 0.9426
        },
        "111": {
            "loss": 0.16611327373844278,
            "acc": 0.94302
        },
        "112": {
            "loss": 0.15904323348913657,
            "acc": 0.94484
        },
        "113": {
            "loss": 0.15521777593685537,
            "acc": 0.9464
        },
        "114": {
            "loss": 0.16501027580036226,
            "acc": 0.94316
        },
        "115": {
            "loss": 0.15695329319180734,
            "acc": 0.94608
        },
        "116": {
            "loss": 0.15440397136999517,
            "acc": 0.94754
        },
        "117": {
            "loss": 0.15172694875951617,
            "acc": 0.9461
        },
        "118": {
            "loss": 0.15057096686547675,
            "acc": 0.94758
        },
        "119": {
            "loss": 0.14785072608562685,
            "acc": 0.94866
        },
        "120": {
            "loss": 0.15034857834391582,
            "acc": 0.94886
        },
        "121": {
            "loss": 0.14783438934427698,
            "acc": 0.94768
        },
        "122": {
            "loss": 0.14496726781853933,
            "acc": 0.94964
        },
        "123": {
            "loss": 0.14326813357794072,
            "acc": 0.95016
        },
        "124": {
            "loss": 0.1389879815928314,
            "acc": 0.95176
        },
        "125": {
            "loss": 0.14278664390373108,
            "acc": 0.95102
        },
        "126": {
            "loss": 0.13844747824208511,
            "acc": 0.95174
        },
        "127": {
            "loss": 0.13796590816448717,
            "acc": 0.95146
        },
        "128": {
            "loss": 0.1351470847130584,
            "acc": 0.95352
        },
        "129": {
            "loss": 0.13344073811036242,
            "acc": 0.95352
        },
        "130": {
            "loss": 0.1373020653110331,
            "acc": 0.95298
        },
        "131": {
            "loss": 0.1286348601912751,
            "acc": 0.95504
        },
        "132": {
            "loss": 0.12273831172939152,
            "acc": 0.9578
        },
        "133": {
            "loss": 0.12888810647380017,
            "acc": 0.95584
        },
        "134": {
            "loss": 0.1246163655844186,
            "acc": 0.95598
        },
        "135": {
            "loss": 0.1256381875223211,
            "acc": 0.95686
        },
        "136": {
            "loss": 0.1309252719268622,
            "acc": 0.95418
        },
        "137": {
            "loss": 0.12360673026203195,
            "acc": 0.95702
        },
        "138": {
            "loss": 0.11582633831997967,
            "acc": 0.95932
        },
        "139": {
            "loss": 0.11723579120491166,
            "acc": 0.95988
        },
        "140": {
            "loss": 0.11332112720803074,
            "acc": 0.96002
        },
        "141": {
            "loss": 0.11161247642753679,
            "acc": 0.96128
        },
        "142": {
            "loss": 0.1131399598953974,
            "acc": 0.96116
        },
        "143": {
            "loss": 0.1086719053156693,
            "acc": 0.96282
        },
        "144": {
            "loss": 0.11027315175613327,
            "acc": 0.96178
        },
        "145": {
            "loss": 0.11224624073928427,
            "acc": 0.96162
        },
        "146": {
            "loss": 0.10421542740424576,
            "acc": 0.96332
        },
        "147": {
            "loss": 0.10603260640960063,
            "acc": 0.96348
        },
        "148": {
            "loss": 0.10113861477550339,
            "acc": 0.96452
        },
        "149": {
            "loss": 0.10342231120371148,
            "acc": 0.9645
        },
        "150": {
            "loss": 0.09403698473616177,
            "acc": 0.96726
        },
        "151": {
            "loss": 0.09901701421250621,
            "acc": 0.96592
        },
        "152": {
            "loss": 0.0956266074943954,
            "acc": 0.96674
        },
        "153": {
            "loss": 0.0972818076143713,
            "acc": 0.9659
        },
        "154": {
            "loss": 0.09709608011290698,
            "acc": 0.96696
        },
        "155": {
            "loss": 0.09410019597167249,
            "acc": 0.96768
        },
        "156": {
            "loss": 0.09325119052701594,
            "acc": 0.96796
        },
        "157": {
            "loss": 0.087099551611468,
            "acc": 0.96904
        },
        "158": {
            "loss": 0.09201221272130222,
            "acc": 0.96846
        },
        "159": {
            "loss": 0.08515573962641608,
            "acc": 0.97052
        },
        "160": {
            "loss": 0.08965977909200637,
            "acc": 0.96912
        },
        "161": {
            "loss": 0.08741201527054658,
            "acc": 0.97014
        },
        "162": {
            "loss": 0.08044884523467334,
            "acc": 0.9721
        },
        "163": {
            "loss": 0.07877082990773042,
            "acc": 0.973
        },
        "164": {
            "loss": 0.08334165277993283,
            "acc": 0.97078
        },
        "165": {
            "loss": 0.07713630605165077,
            "acc": 0.9735
        },
        "166": {
            "loss": 0.07377231936625507,
            "acc": 0.97396
        },
        "167": {
            "loss": 0.08189762612361737,
            "acc": 0.97162
        },
        "168": {
            "loss": 0.0729118401799208,
            "acc": 0.97472
        },
        "169": {
            "loss": 0.0746337958871175,
            "acc": 0.97476
        },
        "170": {
            "loss": 0.07388006108086509,
            "acc": 0.97458
        },
        "171": {
            "loss": 0.0709511846937525,
            "acc": 0.97588
        },
        "172": {
            "loss": 0.06733019949148988,
            "acc": 0.97704
        },
        "173": {
            "loss": 0.06476978338359261,
            "acc": 0.97804
        },
        "174": {
            "loss": 0.06792195706063753,
            "acc": 0.9771
        },
        "175": {
            "loss": 0.0641015125367114,
            "acc": 0.97792
        },
        "176": {
            "loss": 0.0628053721211984,
            "acc": 0.97848
        },
        "177": {
            "loss": 0.059222978782718594,
            "acc": 0.9793
        },
        "178": {
            "loss": 0.060589630590261095,
            "acc": 0.9793
        },
        "179": {
            "loss": 0.057179305890617926,
            "acc": 0.98098
        },
        "180": {
            "loss": 0.05929090321311713,
            "acc": 0.97978
        },
        "181": {
            "loss": 0.058319504165550325,
            "acc": 0.98054
        },
        "182": {
            "loss": 0.05633455082116758,
            "acc": 0.98076
        },
        "183": {
            "loss": 0.05528626755080031,
            "acc": 0.9813
        },
        "184": {
            "loss": 0.05229037777994714,
            "acc": 0.98236
        },
        "185": {
            "loss": 0.05186407822553459,
            "acc": 0.98292
        },
        "186": {
            "loss": 0.05024805338219609,
            "acc": 0.98264
        },
        "187": {
            "loss": 0.049448334413063726,
            "acc": 0.98326
        },
        "188": {
            "loss": 0.04903599774629316,
            "acc": 0.98352
        },
        "189": {
            "loss": 0.04718769703696356,
            "acc": 0.98368
        },
        "190": {
            "loss": 0.045690663089818506,
            "acc": 0.9842
        },
        "191": {
            "loss": 0.04295204232549271,
            "acc": 0.98502
        },
        "192": {
            "loss": 0.04303559823476178,
            "acc": 0.9856
        },
        "193": {
            "loss": 0.039208151008862324,
            "acc": 0.98674
        },
        "194": {
            "loss": 0.04104019364442133,
            "acc": 0.9856
        },
        "195": {
            "loss": 0.0422628898140224,
            "acc": 0.9861
        },
        "196": {
            "loss": 0.03704734381926639,
            "acc": 0.98786
        },
        "197": {
            "loss": 0.03762563053623337,
            "acc": 0.98752
        },
        "198": {
            "loss": 0.0378588881912877,
            "acc": 0.98722
        },
        "199": {
            "loss": 0.03492213645652222,
            "acc": 0.98862
        },
        "200": {
            "loss": 0.03401530055624559,
            "acc": 0.98904
        },
        "201": {
            "loss": 0.03605994085550232,
            "acc": 0.98786
        },
        "202": {
            "loss": 0.03398752659964173,
            "acc": 0.98878
        },
        "203": {
            "loss": 0.032574156941155265,
            "acc": 0.98914
        },
        "204": {
            "loss": 0.033762266768900026,
            "acc": 0.98836
        },
        "205": {
            "loss": 0.03186881395004442,
            "acc": 0.98954
        },
        "206": {
            "loss": 0.02926765650015353,
            "acc": 0.99028
        },
        "207": {
            "loss": 0.028472710157866062,
            "acc": 0.99074
        },
        "208": {
            "loss": 0.02954217863163156,
            "acc": 0.99036
        },
        "209": {
            "loss": 0.026642420880563195,
            "acc": 0.99164
        },
        "210": {
            "loss": 0.027394286298509832,
            "acc": 0.99072
        },
        "211": {
            "loss": 0.02556645577651975,
            "acc": 0.99166
        },
        "212": {
            "loss": 0.023791604141211686,
            "acc": 0.9921
        },
        "213": {
            "loss": 0.026837869970690067,
            "acc": 0.99118
        },
        "214": {
            "loss": 0.02595984910839878,
            "acc": 0.99144
        },
        "215": {
            "loss": 0.024646709272649874,
            "acc": 0.99156
        },
        "216": {
            "loss": 0.02228106874386039,
            "acc": 0.99288
        },
        "217": {
            "loss": 0.021541635056569353,
            "acc": 0.99292
        },
        "218": {
            "loss": 0.019764764822157256,
            "acc": 0.9935
        },
        "219": {
            "loss": 0.02192139627633478,
            "acc": 0.9932
        },
        "220": {
            "loss": 0.02161677831428392,
            "acc": 0.9932
        },
        "221": {
            "loss": 0.020702308214143338,
            "acc": 0.9933
        },
        "222": {
            "loss": 0.01914836166550398,
            "acc": 0.99398
        },
        "223": {
            "loss": 0.018723345465113735,
            "acc": 0.99426
        },
        "224": {
            "loss": 0.018744535587282608,
            "acc": 0.99352
        },
        "225": {
            "loss": 0.01816666820693923,
            "acc": 0.99428
        },
        "226": {
            "loss": 0.01947883680543822,
            "acc": 0.99382
        },
        "227": {
            "loss": 0.01781955652702314,
            "acc": 0.99428
        },
        "228": {
            "loss": 0.016964488347773168,
            "acc": 0.9949
        },
        "229": {
            "loss": 0.017535940838961022,
            "acc": 0.99452
        },
        "230": {
            "loss": 0.016438245926650188,
            "acc": 0.99462
        },
        "231": {
            "loss": 0.016448898133440682,
            "acc": 0.9949
        },
        "232": {
            "loss": 0.015649353322522985,
            "acc": 0.99514
        },
        "233": {
            "loss": 0.01585389954461347,
            "acc": 0.99498
        },
        "234": {
            "loss": 0.015610586115530671,
            "acc": 0.99498
        },
        "235": {
            "loss": 0.017089977289837025,
            "acc": 0.99446
        },
        "236": {
            "loss": 0.016196809739739065,
            "acc": 0.99476
        },
        "237": {
            "loss": 0.016125311110126418,
            "acc": 0.99482
        },
        "238": {
            "loss": 0.015124340876615357,
            "acc": 0.9952
        },
        "239": {
            "loss": 0.015860932154754828,
            "acc": 0.995
        },
        "240": {
            "loss": 0.01709770114170602,
            "acc": 0.99452
        },
        "241": {
            "loss": 0.01434586350889424,
            "acc": 0.99554
        },
        "242": {
            "loss": 0.015056466990117165,
            "acc": 0.99522
        },
        "243": {
            "loss": 0.016223032861445434,
            "acc": 0.99516
        },
        "244": {
            "loss": 0.014783747019180718,
            "acc": 0.99536
        },
        "245": {
            "loss": 0.01527377359254662,
            "acc": 0.99536
        },
        "246": {
            "loss": 0.01475605175486835,
            "acc": 0.9954
        },
        "247": {
            "loss": 0.014332570228487482,
            "acc": 0.99558
        },
        "248": {
            "loss": 0.014744317434166017,
            "acc": 0.99532
        },
        "249": {
            "loss": 0.014872593148534074,
            "acc": 0.9953
        }
    },
    "test": {
        "0": {
            "loss": 1.3792898535728455,
            "acc": 0.5006
        },
        "1": {
            "loss": 1.004788510799408,
            "acc": 0.6386
        },
        "3": {
            "loss": 0.9078679001331329,
            "acc": 0.6827
        },
        "5": {
            "loss": 0.661149297952652,
            "acc": 0.7659
        },
        "7": {
            "loss": 0.6080587923526763,
            "acc": 0.7851
        },
        "9": {
            "loss": 0.5202563500404358,
            "acc": 0.826
        },
        "11": {
            "loss": 0.49763595759868623,
            "acc": 0.831
        },
        "13": {
            "loss": 0.4240414750576019,
            "acc": 0.8567
        },
        "15": {
            "loss": 0.4181032657623291,
            "acc": 0.859
        },
        "17": {
            "loss": 0.35939124405384065,
            "acc": 0.877
        },
        "19": {
            "loss": 0.3478899949789047,
            "acc": 0.8803
        },
        "21": {
            "loss": 0.36465452164411544,
            "acc": 0.8799
        },
        "23": {
            "loss": 0.3295784589648247,
            "acc": 0.889
        },
        "25": {
            "loss": 0.31150703489780424,
            "acc": 0.8935
        },
        "27": {
            "loss": 0.3213295820355415,
            "acc": 0.8912
        },
        "29": {
            "loss": 0.307382934987545,
            "acc": 0.8941
        },
        "31": {
            "loss": 0.3090659111738205,
            "acc": 0.898
        },
        "33": {
            "loss": 0.3014065065979958,
            "acc": 0.897
        },
        "35": {
            "loss": 0.3091526019573212,
            "acc": 0.9
        },
        "37": {
            "loss": 0.29158659398555753,
            "acc": 0.9041
        },
        "39": {
            "loss": 0.30762077510356906,
            "acc": 0.9002
        },
        "41": {
            "loss": 0.29507698088884354,
            "acc": 0.9018
        },
        "43": {
            "loss": 0.2781335201859474,
            "acc": 0.9101
        },
        "45": {
            "loss": 0.29521842300891876,
            "acc": 0.9026
        },
        "47": {
            "loss": 0.2529300057888031,
            "acc": 0.9146
        },
        "49": {
            "loss": 0.2922437798976898,
            "acc": 0.9041
        },
        "51": {
            "loss": 0.29361236840486526,
            "acc": 0.9071
        },
        "53": {
            "loss": 0.2506280180811882,
            "acc": 0.9152
        },
        "55": {
            "loss": 0.2566638857126236,
            "acc": 0.9175
        },
        "57": {
            "loss": 0.238211809694767,
            "acc": 0.9225
        },
        "59": {
            "loss": 0.24954752027988433,
            "acc": 0.9144
        },
        "61": {
            "loss": 0.28963326930999755,
            "acc": 0.9085
        },
        "63": {
            "loss": 0.24382995337247848,
            "acc": 0.9191
        },
        "65": {
            "loss": 0.25897552639245985,
            "acc": 0.9111
        },
        "67": {
            "loss": 0.268899427652359,
            "acc": 0.914
        },
        "69": {
            "loss": 0.2693224173784256,
            "acc": 0.9157
        },
        "71": {
            "loss": 0.2483004152774811,
            "acc": 0.9173
        },
        "73": {
            "loss": 0.24396055668592453,
            "acc": 0.9231
        },
        "75": {
            "loss": 0.25824803292751314,
            "acc": 0.9174
        },
        "77": {
            "loss": 0.23628887116909028,
            "acc": 0.9255
        },
        "79": {
            "loss": 0.23389400362968446,
            "acc": 0.9234
        },
        "81": {
            "loss": 0.24134291887283324,
            "acc": 0.9199
        },
        "83": {
            "loss": 0.2491414301097393,
            "acc": 0.9211
        },
        "85": {
            "loss": 0.22663541927933692,
            "acc": 0.9292
        },
        "87": {
            "loss": 0.22930427372455597,
            "acc": 0.9285
        },
        "89": {
            "loss": 0.22687575340270996,
            "acc": 0.9261
        },
        "91": {
            "loss": 0.22967445284128188,
            "acc": 0.9285
        },
        "93": {
            "loss": 0.22740560695528983,
            "acc": 0.9299
        },
        "95": {
            "loss": 0.24419200122356416,
            "acc": 0.9225
        },
        "97": {
            "loss": 0.2197196114063263,
            "acc": 0.929
        },
        "99": {
            "loss": 0.2552019488811493,
            "acc": 0.9212
        },
        "101": {
            "loss": 0.2373482744395733,
            "acc": 0.9256
        },
        "103": {
            "loss": 0.22356128826737404,
            "acc": 0.9289
        },
        "105": {
            "loss": 0.23216117829084396,
            "acc": 0.9299
        },
        "107": {
            "loss": 0.22808541283011435,
            "acc": 0.9295
        },
        "109": {
            "loss": 0.21634344026446342,
            "acc": 0.9301
        },
        "111": {
            "loss": 0.21942791789770127,
            "acc": 0.9332
        },
        "113": {
            "loss": 0.22639474973082543,
            "acc": 0.932
        },
        "115": {
            "loss": 0.2215052381157875,
            "acc": 0.932
        },
        "117": {
            "loss": 0.2238486559689045,
            "acc": 0.9313
        },
        "119": {
            "loss": 0.2260180616378784,
            "acc": 0.9317
        },
        "121": {
            "loss": 0.2285964584350586,
            "acc": 0.9301
        },
        "123": {
            "loss": 0.22291549265384675,
            "acc": 0.934
        },
        "125": {
            "loss": 0.2220345474779606,
            "acc": 0.9304
        },
        "127": {
            "loss": 0.20798859551548957,
            "acc": 0.9377
        },
        "129": {
            "loss": 0.25316772431135176,
            "acc": 0.9263
        },
        "131": {
            "loss": 0.2034419672191143,
            "acc": 0.9383
        },
        "133": {
            "loss": 0.20576480880379677,
            "acc": 0.9369
        },
        "135": {
            "loss": 0.20452826872467994,
            "acc": 0.9392
        },
        "137": {
            "loss": 0.21118584036827087,
            "acc": 0.9339
        },
        "139": {
            "loss": 0.20331912532448768,
            "acc": 0.9393
        },
        "141": {
            "loss": 0.2314854693412781,
            "acc": 0.9333
        },
        "143": {
            "loss": 0.20418817028403283,
            "acc": 0.9384
        },
        "145": {
            "loss": 0.22031123757362367,
            "acc": 0.937
        },
        "147": {
            "loss": 0.20787963077425956,
            "acc": 0.9421
        },
        "149": {
            "loss": 0.22229282960295677,
            "acc": 0.9378
        },
        "151": {
            "loss": 0.21420383751392363,
            "acc": 0.9403
        },
        "153": {
            "loss": 0.1928093107044697,
            "acc": 0.9406
        },
        "155": {
            "loss": 0.19945183962583543,
            "acc": 0.943
        },
        "157": {
            "loss": 0.207803708165884,
            "acc": 0.9408
        },
        "159": {
            "loss": 0.20811064571142196,
            "acc": 0.9434
        },
        "161": {
            "loss": 0.21006754130125047,
            "acc": 0.9406
        },
        "163": {
            "loss": 0.20280403584241868,
            "acc": 0.9425
        },
        "165": {
            "loss": 0.20471078872680665,
            "acc": 0.9466
        },
        "167": {
            "loss": 0.20233140826225282,
            "acc": 0.9426
        },
        "169": {
            "loss": 0.2161995640397072,
            "acc": 0.942
        },
        "171": {
            "loss": 0.2098721146583557,
            "acc": 0.9438
        },
        "173": {
            "loss": 0.21411218672990798,
            "acc": 0.9453
        },
        "175": {
            "loss": 0.2109688140451908,
            "acc": 0.9433
        },
        "177": {
            "loss": 0.1950916039943695,
            "acc": 0.9487
        },
        "179": {
            "loss": 0.20179904371500015,
            "acc": 0.9455
        },
        "181": {
            "loss": 0.20077210322022437,
            "acc": 0.9464
        },
        "183": {
            "loss": 0.2086840334534645,
            "acc": 0.9481
        },
        "185": {
            "loss": 0.20948946937918664,
            "acc": 0.9481
        },
        "187": {
            "loss": 0.19724978983402253,
            "acc": 0.9488
        },
        "189": {
            "loss": 0.19673774659633636,
            "acc": 0.9512
        },
        "191": {
            "loss": 0.20434166073799134,
            "acc": 0.9489
        },
        "193": {
            "loss": 0.20505117267370224,
            "acc": 0.9472
        },
        "195": {
            "loss": 0.2115371862053871,
            "acc": 0.9471
        },
        "197": {
            "loss": 0.19362819150090219,
            "acc": 0.9523
        },
        "199": {
            "loss": 0.20243983283638955,
            "acc": 0.9498
        },
        "201": {
            "loss": 0.20952801391482354,
            "acc": 0.9501
        },
        "203": {
            "loss": 0.1993783977627754,
            "acc": 0.9521
        },
        "205": {
            "loss": 0.20980528846383095,
            "acc": 0.9509
        },
        "207": {
            "loss": 0.20901310503482817,
            "acc": 0.9498
        },
        "209": {
            "loss": 0.20793256357312204,
            "acc": 0.9517
        },
        "211": {
            "loss": 0.2068021935224533,
            "acc": 0.9523
        },
        "213": {
            "loss": 0.2057925659418106,
            "acc": 0.9523
        },
        "215": {
            "loss": 0.2053673516213894,
            "acc": 0.9514
        },
        "217": {
            "loss": 0.19879925869405268,
            "acc": 0.9529
        },
        "219": {
            "loss": 0.20040746197104453,
            "acc": 0.9533
        },
        "221": {
            "loss": 0.20116283528506756,
            "acc": 0.9556
        },
        "223": {
            "loss": 0.20013550385832787,
            "acc": 0.9561
        },
        "225": {
            "loss": 0.20149600386619568,
            "acc": 0.9556
        },
        "227": {
            "loss": 0.20355344608426093,
            "acc": 0.9553
        },
        "229": {
            "loss": 0.20163778945803643,
            "acc": 0.9554
        },
        "231": {
            "loss": 0.20234888553619385,
            "acc": 0.9547
        },
        "233": {
            "loss": 0.20456083983182907,
            "acc": 0.9554
        },
        "235": {
            "loss": 0.20358612313866614,
            "acc": 0.9551
        },
        "237": {
            "loss": 0.20327427119016647,
            "acc": 0.9551
        },
        "239": {
            "loss": 0.20553239330649375,
            "acc": 0.9544
        },
        "241": {
            "loss": 0.20332553535699843,
            "acc": 0.9552
        },
        "243": {
            "loss": 0.20367712289094925,
            "acc": 0.9555
        },
        "245": {
            "loss": 0.2025564706325531,
            "acc": 0.9562
        },
        "247": {
            "loss": 0.20463673904538154,
            "acc": 0.9557
        },
        "249": {
            "loss": 0.2054194937646389,
            "acc": 0.9556
        }
    },
    "best": {
        "best_epoch": 245,
        "best_acc": 95.62
    }
}